{
"siderbar": [
  {
    "link": "/dashboard",
    "text": "Dashboard",
    "icon": "feather-home"
  },
  {
    "link": "/dashboard/profile",
    "text": "My Profile",
    "icon": "feather-user"
  },
  {
    "link": "/dashboard/enrolled-course",
    "text": "Enrolled Courses",
    "icon": "feather-book-open"
  },
  {
    "link": "/dashboard/wishlist",
    "text": "Wishlist",
    "icon": "feather-bookmark"
  },
  {
    "link": "/dashboard/reviews",
    "text": "Reviews",
    "icon": "feather-star"
  },
  {
    "link": "/dashboard/quiz-attempts",
    "text": "My Quiz Attempts",
    "icon": "feather-help-circle"
  },
  {
    "link": "/dashboard/order-history",
    "text": "Order History",
    "icon": "feather-shopping-bag"
  },
  {
    "link": "/dashboard/settings",
    "text": "Settings",
    "icon": "feather-settings"
  },
  {
    "link": "/",
    "text": "Logout",
    "icon": "feather-log-out"
  }
]
}
